noumenon/__init__.py
noumenon-0.0.1a1.dist-info/METADATA
noumenon-0.0.1a1.dist-info/WHEEL
noumenon-0.0.1a1.dist-info/licenses/LICENSE
noumenon-0.0.1a1.dist-info/RECORD
