Metadata-Version: 2.4
Name: noumenon
Version: 0.0.1a1
Summary: A Python package for Noumenon
Project-URL: Homepage, https://github.com/HZACODE/Noumenon
Author-email: Noumenon Team <noumenon@noumenon.org>
License: MIT License
License-File: LICENSE
Classifier: Development Status :: 2 - Pre-Alpha
Classifier: Intended Audience :: Developers
Classifier: License :: OSI Approved :: MIT License
Classifier: Operating System :: OS Independent
Classifier: Programming Language :: Python :: 3
Classifier: Programming Language :: Python :: 3.7
Classifier: Programming Language :: Python :: 3.8
Classifier: Programming Language :: Python :: 3.9
Classifier: Programming Language :: Python :: 3.10
Classifier: Programming Language :: Python :: 3.11
Requires-Python: >=3.7
